{
  "metadata": {
    "analysis": "P1 - Folio Personality Clusters",
    "description": "Unsupervised clustering of folios by burden indices",
    "n_folios": 227,
    "n_features": 9,
    "n_clusters": 4
  },
  "clustering": {
    "n_clusters": 4,
    "silhouette_scores": [
      [
        2,
        0.4240011359716046
      ],
      [
        3,
        0.47031094782972344
      ],
      [
        4,
        0.5580807052561274
      ],
      [
        5,
        0.5529422903920707
      ],
      [
        6,
        0.5167128902659154
      ],
      [
        7,
        0.49444467268851905
      ],
      [
        8,
        0.491454015514474
      ],
      [
        9,
        0.48778359780850283
      ],
      [
        10,
        0.48449499489039505
      ]
    ],
    "labels": {
      "f100r": 0,
      "f100v": 0,
      "f101r1": 0,
      "f101v2": 0,
      "f102r1": 0,
      "f102r2": 0,
      "f102v1": 0,
      "f102v2": 0,
      "f103r": 1,
      "f103v": 1,
      "f104r": 1,
      "f104v": 1,
      "f105r": 1,
      "f105v": 1,
      "f106r": 1,
      "f106v": 1,
      "f107r": 1,
      "f107v": 1,
      "f108r": 1,
      "f108v": 1,
      "f10r": 0,
      "f10v": 0,
      "f111r": 1,
      "f111v": 1,
      "f112r": 1,
      "f112v": 1,
      "f113r": 1,
      "f113v": 1,
      "f114r": 1,
      "f114v": 1,
      "f115r": 1,
      "f115v": 1,
      "f116r": 1,
      "f116v": 3,
      "f11r": 0,
      "f11v": 0,
      "f13r": 2,
      "f13v": 0,
      "f14r": 0,
      "f14v": 0,
      "f15r": 0,
      "f15v": 0,
      "f16r": 0,
      "f16v": 0,
      "f17r": 0,
      "f17v": 0,
      "f18r": 0,
      "f18v": 2,
      "f19r": 0,
      "f19v": 2,
      "f1r": 0,
      "f1v": 0,
      "f20r": 0,
      "f20v": 0,
      "f21r": 0,
      "f21v": 0,
      "f22r": 0,
      "f22v": 0,
      "f23r": 0,
      "f23v": 0,
      "f24r": 0,
      "f24v": 0,
      "f25r": 0,
      "f25v": 0,
      "f26r": 1,
      "f26v": 1,
      "f27r": 0,
      "f27v": 2,
      "f28r": 0,
      "f28v": 0,
      "f29r": 0,
      "f29v": 0,
      "f2r": 0,
      "f2v": 0,
      "f30r": 0,
      "f30v": 0,
      "f31r": 1,
      "f31v": 1,
      "f32r": 0,
      "f32v": 0,
      "f33r": 1,
      "f33v": 1,
      "f34r": 1,
      "f34v": 1,
      "f35r": 0,
      "f35v": 0,
      "f36r": 0,
      "f36v": 0,
      "f37r": 0,
      "f37v": 0,
      "f38r": 0,
      "f38v": 0,
      "f39r": 1,
      "f39v": 1,
      "f3r": 0,
      "f3v": 0,
      "f40r": 1,
      "f40v": 1,
      "f41r": 2,
      "f41v": 1,
      "f42r": 0,
      "f42v": 0,
      "f43r": 1,
      "f43v": 1,
      "f44r": 0,
      "f44v": 0,
      "f45r": 0,
      "f45v": 0,
      "f46r": 1,
      "f46v": 1,
      "f47r": 0,
      "f47v": 0,
      "f48r": 1,
      "f48v": 1,
      "f49r": 0,
      "f49v": 0,
      "f4r": 0,
      "f4v": 0,
      "f50r": 1,
      "f50v": 1,
      "f51r": 0,
      "f51v": 0,
      "f52r": 0,
      "f52v": 0,
      "f53r": 0,
      "f53v": 0,
      "f54r": 0,
      "f54v": 0,
      "f55r": 1,
      "f55v": 1,
      "f56r": 0,
      "f56v": 0,
      "f57r": 1,
      "f57v": 3,
      "f58r": 0,
      "f58v": 0,
      "f5r": 0,
      "f5v": 0,
      "f65r": 2,
      "f65v": 3,
      "f66r": 1,
      "f66v": 1,
      "f67r1": 3,
      "f67r2": 2,
      "f67v1": 3,
      "f67v2": 3,
      "f68r1": 3,
      "f68r2": 3,
      "f68r3": 3,
      "f68v1": 3,
      "f68v2": 3,
      "f68v3": 3,
      "f69r": 3,
      "f69v": 3,
      "f6r": 0,
      "f6v": 0,
      "f70r1": 3,
      "f70r2": 3,
      "f70v1": 3,
      "f70v2": 3,
      "f71r": 3,
      "f71v": 3,
      "f72r1": 3,
      "f72r2": 3,
      "f72r3": 3,
      "f72v1": 3,
      "f72v2": 3,
      "f72v3": 3,
      "f73r": 3,
      "f73v": 3,
      "f75r": 1,
      "f75v": 1,
      "f76r": 1,
      "f76v": 1,
      "f77r": 1,
      "f77v": 1,
      "f78r": 1,
      "f78v": 1,
      "f79r": 1,
      "f79v": 1,
      "f7r": 0,
      "f7v": 0,
      "f80r": 1,
      "f80v": 1,
      "f81r": 1,
      "f81v": 1,
      "f82r": 1,
      "f82v": 1,
      "f83r": 1,
      "f83v": 1,
      "f84r": 1,
      "f84v": 1,
      "f85r1": 1,
      "f85r2": 1,
      "f85v2": 1,
      "f86v3": 1,
      "f86v4": 1,
      "f86v5": 2,
      "f86v6": 1,
      "f87r": 2,
      "f87v": 2,
      "f88r": 0,
      "f88v": 0,
      "f89r1": 0,
      "f89r2": 0,
      "f89v1": 0,
      "f89v2": 0,
      "f8r": 0,
      "f8v": 0,
      "f90r1": 0,
      "f90r2": 0,
      "f90v1": 0,
      "f90v2": 0,
      "f93r": 0,
      "f93v": 0,
      "f94r": 1,
      "f94v": 1,
      "f95r1": 1,
      "f95r2": 1,
      "f95v1": 1,
      "f95v2": 1,
      "f96r": 0,
      "f96v": 0,
      "f99r": 0,
      "f99v": 0,
      "f9r": 0,
      "f9v": 0
    }
  },
  "cluster_analysis": {
    "0": {
      "n_folios": 108,
      "folios": [
        "f100r",
        "f100v",
        "f101r1",
        "f101v2",
        "f102r1",
        "f102r2",
        "f102v1",
        "f102v2",
        "f10r",
        "f10v",
        "f11r",
        "f11v",
        "f13v",
        "f14r",
        "f14v",
        "f15r",
        "f15v",
        "f16r",
        "f16v",
        "f17r",
        "f17v",
        "f18r",
        "f19r",
        "f1r",
        "f1v",
        "f20r",
        "f20v",
        "f21r",
        "f21v",
        "f22r",
        "f22v",
        "f23r",
        "f23v",
        "f24r",
        "f24v",
        "f25r",
        "f25v",
        "f27r",
        "f28r",
        "f28v",
        "f29r",
        "f29v",
        "f2r",
        "f2v",
        "f30r",
        "f30v",
        "f32r",
        "f32v",
        "f35r",
        "f35v",
        "f36r",
        "f36v",
        "f37r",
        "f37v",
        "f38r",
        "f38v",
        "f3r",
        "f3v",
        "f42r",
        "f42v",
        "f44r",
        "f44v",
        "f45r",
        "f45v",
        "f47r",
        "f47v",
        "f49r",
        "f49v",
        "f4r",
        "f4v",
        "f51r",
        "f51v",
        "f52r",
        "f52v",
        "f53r",
        "f53v",
        "f54r",
        "f54v",
        "f56r",
        "f56v",
        "f58r",
        "f58v",
        "f5r",
        "f5v",
        "f6r",
        "f6v",
        "f7r",
        "f7v",
        "f88r",
        "f88v",
        "f89r1",
        "f89r2",
        "f89v1",
        "f89v2",
        "f8r",
        "f8v",
        "f90r1",
        "f90r2",
        "f90v1",
        "f90v2",
        "f93r",
        "f93v",
        "f96r",
        "f96v",
        "f99r",
        "f99v",
        "f9r",
        "f9v"
      ],
      "systems": {
        "A": 108
      },
      "dominant_system": "A",
      "ht_stats": {
        "mean": 0.163,
        "std": 0.0468,
        "statuses": {
          "NORMAL": 108
        }
      },
      "burden_stats": {
        "cognitive_mean": 0.031,
        "tension_mean": null,
        "n_b_folios": 0
      },
      "quire_distribution": {
        "S": 10,
        "B": 13,
        "C": 14,
        "A": 16,
        "D": 11,
        "E": 8,
        "F": 8,
        "G": 12,
        "H": 2,
        "O": 10,
        "Q": 4
      }
    },
    "1": {
      "n_folios": 81,
      "folios": [
        "f103r",
        "f103v",
        "f104r",
        "f104v",
        "f105r",
        "f105v",
        "f106r",
        "f106v",
        "f107r",
        "f107v",
        "f108r",
        "f108v",
        "f111r",
        "f111v",
        "f112r",
        "f112v",
        "f113r",
        "f113v",
        "f114r",
        "f114v",
        "f115r",
        "f115v",
        "f116r",
        "f26r",
        "f26v",
        "f31r",
        "f31v",
        "f33r",
        "f33v",
        "f34r",
        "f34v",
        "f39r",
        "f39v",
        "f40r",
        "f40v",
        "f41v",
        "f43r",
        "f43v",
        "f46r",
        "f46v",
        "f48r",
        "f48v",
        "f50r",
        "f50v",
        "f55r",
        "f55v",
        "f57r",
        "f66r",
        "f66v",
        "f75r",
        "f75v",
        "f76r",
        "f76v",
        "f77r",
        "f77v",
        "f78r",
        "f78v",
        "f79r",
        "f79v",
        "f80r",
        "f80v",
        "f81r",
        "f81v",
        "f82r",
        "f82v",
        "f83r",
        "f83v",
        "f84r",
        "f84v",
        "f85r1",
        "f85r2",
        "f85v2",
        "f86v3",
        "f86v4",
        "f86v6",
        "f94r",
        "f94v",
        "f95r1",
        "f95r2",
        "f95v1",
        "f95v2"
      ],
      "systems": {
        "B": 81
      },
      "dominant_system": "B",
      "ht_stats": {
        "mean": 0.1461,
        "std": 0.0418,
        "statuses": {
          "NORMAL": 81
        }
      },
      "burden_stats": {
        "cognitive_mean": -0.28,
        "tension_mean": 0.017,
        "n_b_folios": 81
      },
      "quire_distribution": {
        "T": 23,
        "D": 4,
        "E": 8,
        "F": 7,
        "G": 4,
        "H": 3,
        "M": 20,
        "N": 6,
        "Q": 6
      }
    },
    "2": {
      "n_folios": 10,
      "folios": [
        "f13r",
        "f18v",
        "f19v",
        "f27v",
        "f41r",
        "f65r",
        "f67r2",
        "f86v5",
        "f87r",
        "f87v"
      ],
      "systems": {
        "A": 6,
        "B": 2,
        "AZC": 2
      },
      "dominant_system": "A",
      "ht_stats": {
        "mean": 0.2967,
        "std": 0.0222,
        "statuses": {
          "HOTSPOT": 10
        }
      },
      "burden_stats": {
        "cognitive_mean": 2.483,
        "tension_mean": -0.679,
        "n_b_folios": 2
      },
      "quire_distribution": {
        "B": 1,
        "C": 2,
        "D": 1,
        "F": 1,
        "H": 1,
        "I": 1,
        "N": 1,
        "O": 2
      }
    },
    "3": {
      "n_folios": 28,
      "folios": [
        "f116v",
        "f57v",
        "f65v",
        "f67r1",
        "f67v1",
        "f67v2",
        "f68r1",
        "f68r2",
        "f68r3",
        "f68v1",
        "f68v2",
        "f68v3",
        "f69r",
        "f69v",
        "f70r1",
        "f70r2",
        "f70v1",
        "f70v2",
        "f71r",
        "f71v",
        "f72r1",
        "f72r2",
        "f72r3",
        "f72v1",
        "f72v2",
        "f72v3",
        "f73r",
        "f73v"
      ],
      "systems": {
        "AZC": 28
      },
      "dominant_system": "AZC",
      "ht_stats": {
        "mean": 0.1507,
        "std": 0.0554,
        "statuses": {
          "DESERT": 1,
          "NORMAL": 27
        }
      },
      "burden_stats": {
        "cognitive_mean": -0.195,
        "tension_mean": null,
        "n_b_folios": 0
      },
      "quire_distribution": {
        "T": 1,
        "H": 2,
        "I": 9,
        "J": 6,
        "K": 8,
        "L": 2
      }
    }
  },
  "cluster_characters": {
    "0": {
      "traits": [
        "A-pure"
      ],
      "label": "A-pure"
    },
    "1": {
      "traits": [
        "B-pure"
      ],
      "label": "B-pure"
    },
    "2": {
      "traits": [
        "A-dominant",
        "high-HT",
        "low-tension",
        "10-hotspots"
      ],
      "label": "A-dominant | high-HT | low-tension | 10-hotspots"
    },
    "3": {
      "traits": [
        "AZC-pure",
        "1-deserts"
      ],
      "label": "AZC-pure | 1-deserts"
    }
  },
  "validity_tests": {
    "system_separation": {
      "chi2": 432.74,
      "p_value": 0.0,
      "significant": true
    },
    "ht_separation": {
      "h_statistic": 34.77,
      "p_value": 0.0,
      "significant": true
    }
  },
  "anomalies": [
    {
      "folio": "f41r",
      "cluster": 2,
      "expected_system": "A",
      "actual_system": "B",
      "ht_density": 0.2965,
      "ht_status": "HOTSPOT",
      "reason": "B folio in A-dominant cluster"
    },
    {
      "folio": "f65r",
      "cluster": 2,
      "expected_system": "A",
      "actual_system": "AZC",
      "ht_density": 0.3333,
      "ht_status": "HOTSPOT",
      "reason": "AZC folio in A-dominant cluster"
    },
    {
      "folio": "f67r2",
      "cluster": 2,
      "expected_system": "A",
      "actual_system": "AZC",
      "ht_density": 0.2936,
      "ht_status": "HOTSPOT",
      "reason": "AZC folio in A-dominant cluster"
    },
    {
      "folio": "f86v5",
      "cluster": 2,
      "expected_system": "A",
      "actual_system": "B",
      "ht_density": 0.2775,
      "ht_status": "HOTSPOT",
      "reason": "B folio in A-dominant cluster"
    }
  ],
  "key_findings": [
    {
      "finding": "Clusters separate by system",
      "chi2": 432.74,
      "p_value": 0.0,
      "interpretation": "System identity drives clustering"
    },
    {
      "finding": "Clusters separate by HT level",
      "h_statistic": 34.77,
      "p_value": 0.0,
      "interpretation": "HT density is a major clustering dimension"
    },
    {
      "finding": "4 cross-system anomalies",
      "interpretation": "Some folios cluster by HT/burden rather than system"
    }
  ]
}